book_cataloguing/__init__.py
book_cataloguing/author_titles.txt
book_cataloguing/contents.py
book_cataloguing/lowercase_author_words.txt
book_cataloguing/lowercase_title_words.txt
book_cataloguing/mac_surnames.txt
book_cataloguing-1.0.0.dist-info/METADATA
book_cataloguing-1.0.0.dist-info/WHEEL
book_cataloguing-1.0.0.dist-info/licenses/LICENSE
book_cataloguing-1.0.0.dist-info/RECORD
