Metadata-Version: 2.4
Name: book-cataloguing
Version: 1.0.0
Summary: Correctly capitalize and sort the titles and authors of books.
Project-URL: Homepage, https://github.com/PT-Hrothgar/book-cataloguing
Author: PT-Hrothgar
License-Expression: MIT
License-File: LICENSE
Classifier: Development Status :: 4 - Beta
Classifier: License :: OSI Approved :: MIT License
Classifier: Operating System :: OS Independent
Classifier: Programming Language :: Python :: 3
Requires-Python: >=3.9
Requires-Dist: num2words>=0.5.5
Requires-Dist: roman-numerals>=3.0.0
